supercov/__init__.py
pytest_supercov-0.0.0.dist-info/LICENSE
pytest_supercov-0.0.0.dist-info/METADATA
pytest_supercov-0.0.0.dist-info/WHEEL
pytest_supercov-0.0.0.dist-info/top_level.txt
pytest_supercov-0.0.0.dist-info/RECORD
